jaical/__init__.py
QX_jdcal-0.0.2.dist-info/METADATA
QX_jdcal-0.0.2.dist-info/WHEEL
QX_jdcal-0.0.2.dist-info/top_level.txt
QX_jdcal-0.0.2.dist-info/RECORD
