Metadata-Version: 2.1
Name: QX-jdcal
Version: 0.0.2
Summary: A very basic calculator
Home-page: UNKNOWN
Author: jaideep 
Author-email: jaideepkaushal2@gmail.com
License: MIT
Keywords: calculator
Platform: UNKNOWN
Requires-Dist: numpy
Requires-Dist: torch
Requires-Dist: pillow
Requires-Dist: os
